adbasicapi/__init__.py
adbasicapi/api.py
adbasicapi/cli.py
adbasicapi-0.4.0.dist-info/AUTHORS.rst
adbasicapi-0.4.0.dist-info/LICENSE
adbasicapi-0.4.0.dist-info/METADATA
adbasicapi-0.4.0.dist-info/WHEEL
adbasicapi-0.4.0.dist-info/entry_points.txt
adbasicapi-0.4.0.dist-info/top_level.txt
adbasicapi-0.4.0.dist-info/RECORD
